setup.py
distributions_amiref/Binomialdistribution.py
distributions_amiref/Gaussiandistribution.py
distributions_amiref/Generaldistribution.py
distributions_amiref/__init__.py
distributions_amiref.egg-info/PKG-INFO
distributions_amiref.egg-info/SOURCES.txt
distributions_amiref.egg-info/dependency_links.txt
distributions_amiref.egg-info/not-zip-safe
distributions_amiref.egg-info/top_level.txt