Metadata-Version: 2.1
Name: distributions-amiref
Version: 0.1
Summary: Gaussian distributions
License: UNKNOWN
Platform: UNKNOWN
